ribot/__init__.py
ribot/control/__init__.py
ribot/control/arm_kinematics.py
ribot/control/controller_servers.py
ribot/controller.py
ribot/py.typed
ribot/sample_main.py
ribot/tests/__init__.py
ribot/tests/test_controller.py
ribot/tests/test_kinematics.py
ribot/utils/__init__.py
ribot/utils/algebra.py
ribot/utils/fifo_lock.py
ribot/utils/general.py
ribot/utils/messages.py
ribot/utils/prints.py
ribot/utils/version.py
ribot_controller-0.3.12.dist-info/METADATA
ribot_controller-0.3.12.dist-info/WHEEL
ribot_controller-0.3.12.dist-info/RECORD
